senaite.core.supermodel-1.2.1-py2.7-nspkg.pth
senaite/core/supermodel/__init__.py
senaite/core/supermodel/configure.zcml
senaite/core/supermodel/decorators.py
senaite/core/supermodel/interfaces.py
senaite/core/supermodel/model.py
senaite/core/supermodel/tests/__init__.py
senaite/core/supermodel/tests/base.py
senaite/core/supermodel/tests/test_doctests.py
senaite/core/supermodel/tests/test_setup.py
senaite.core.supermodel-1.2.1.dist-info/LICENSE
senaite.core.supermodel-1.2.1.dist-info/METADATA
senaite.core.supermodel-1.2.1.dist-info/WHEEL
senaite.core.supermodel-1.2.1.dist-info/entry_points.txt
senaite.core.supermodel-1.2.1.dist-info/namespace_packages.txt
senaite.core.supermodel-1.2.1.dist-info/top_level.txt
senaite.core.supermodel-1.2.1.dist-info/RECORD
