Metadata-Version: 2.1
Name: senaite.core.supermodel
Version: 1.2.1
Summary: A beautiful content wrapper for SENAITE that you will love
Home-page: https://github.com/senaite/senaite.core.supermodel
Author: SENAITE Foundation
Author-email: hello@senaite.com
License: GPLv2
Platform: UNKNOWN
Classifier: Framework :: Plone
Classifier: Framework :: Zope2
Classifier: Programming Language :: Python
Classifier: Development Status :: 5 - Production/Stable
Classifier: License :: OSI Approved :: GNU General Public License v2 (GPLv2)
Requires-Dist: setuptools
Requires-Dist: senaite.core
Provides-Extra: test
Requires-Dist: Products.PloneTestCase ; extra == 'test'
Requires-Dist: plone.app.testing ; extra == 'test'
Requires-Dist: robotsuite ; extra == 'test'
Requires-Dist: unittest2 ; extra == 'test'
